{
  "$schema": "https://raw.githubusercontent.com/spdx/spdx-spec/v2.2.1/schemas/spdx-schema.json",
  "spdxVersion": "SPDX-2.2",
  "dataLicense": "CC0-1.0",
  "SPDXID": "SPDXRef-DOCUMENT",
  "documentNamespace": "https://spdx.org/spdxdocs/sdl2-mixer-x64-mingw-dynamic-2.8.1#2-5911f614-ed1c-469f-8212-084679f51e28",
  "name": "sdl2-mixer:x64-mingw-dynamic@2.8.1#2 507207a94fadc9c7fb3f777cd75f945edfaac8c800325bfd997c82d47a9aa092",
  "creationInfo": {
    "creators": [
      "Tool: vcpkg-2025-09-03-4580816534ed8fd9634ac83d46471440edd82dfe"
    ],
    "created": "2025-11-29T07:36:01Z"
  },
  "relationships": [
    {
      "spdxElementId": "SPDXRef-port",
      "relationshipType": "GENERATES",
      "relatedSpdxElement": "SPDXRef-binary"
    },
    {
      "spdxElementId": "SPDXRef-port",
      "relationshipType": "CONTAINS",
      "relatedSpdxElement": "SPDXRef-port-file-0"
    },
    {
      "spdxElementId": "SPDXRef-port",
      "relationshipType": "CONTAINS",
      "relatedSpdxElement": "SPDXRef-port-file-1"
    },
    {
      "spdxElementId": "SPDXRef-port",
      "relationshipType": "CONTAINS",
      "relatedSpdxElement": "SPDXRef-port-file-2"
    },
    {
      "spdxElementId": "SPDXRef-port",
      "relationshipType": "CONTAINS",
      "relatedSpdxElement": "SPDXRef-port-file-3"
    },
    {
      "spdxElementId": "SPDXRef-port-file-3",
      "relationshipType": "DEPENDENCY_MANIFEST_OF",
      "relatedSpdxElement": "SPDXRef-port"
    },
    {
      "spdxElementId": "SPDXRef-binary",
      "relationshipType": "CONTAINS",
      "relatedSpdxElement": "SPDXRef-binary-file-0"
    },
    {
      "spdxElementId": "SPDXRef-binary",
      "relationshipType": "CONTAINS",
      "relatedSpdxElement": "SPDXRef-binary-file-1"
    },
    {
      "spdxElementId": "SPDXRef-binary",
      "relationshipType": "CONTAINS",
      "relatedSpdxElement": "SPDXRef-binary-file-2"
    },
    {
      "spdxElementId": "SPDXRef-binary",
      "relationshipType": "CONTAINS",
      "relatedSpdxElement": "SPDXRef-binary-file-3"
    },
    {
      "spdxElementId": "SPDXRef-binary",
      "relationshipType": "CONTAINS",
      "relatedSpdxElement": "SPDXRef-binary-file-4"
    },
    {
      "spdxElementId": "SPDXRef-binary",
      "relationshipType": "CONTAINS",
      "relatedSpdxElement": "SPDXRef-binary-file-5"
    },
    {
      "spdxElementId": "SPDXRef-binary",
      "relationshipType": "CONTAINS",
      "relatedSpdxElement": "SPDXRef-binary-file-6"
    },
    {
      "spdxElementId": "SPDXRef-binary",
      "relationshipType": "CONTAINS",
      "relatedSpdxElement": "SPDXRef-binary-file-7"
    },
    {
      "spdxElementId": "SPDXRef-binary",
      "relationshipType": "CONTAINS",
      "relatedSpdxElement": "SPDXRef-binary-file-8"
    },
    {
      "spdxElementId": "SPDXRef-binary",
      "relationshipType": "CONTAINS",
      "relatedSpdxElement": "SPDXRef-binary-file-9"
    },
    {
      "spdxElementId": "SPDXRef-binary",
      "relationshipType": "CONTAINS",
      "relatedSpdxElement": "SPDXRef-binary-file-10"
    },
    {
      "spdxElementId": "SPDXRef-binary",
      "relationshipType": "CONTAINS",
      "relatedSpdxElement": "SPDXRef-binary-file-11"
    },
    {
      "spdxElementId": "SPDXRef-binary",
      "relationshipType": "CONTAINS",
      "relatedSpdxElement": "SPDXRef-binary-file-12"
    },
    {
      "spdxElementId": "SPDXRef-binary",
      "relationshipType": "CONTAINS",
      "relatedSpdxElement": "SPDXRef-binary-file-13"
    },
    {
      "spdxElementId": "SPDXRef-binary",
      "relationshipType": "CONTAINS",
      "relatedSpdxElement": "SPDXRef-binary-file-14"
    },
    {
      "spdxElementId": "SPDXRef-binary",
      "relationshipType": "CONTAINS",
      "relatedSpdxElement": "SPDXRef-binary-file-15"
    }
  ],
  "packages": [
    {
      "name": "sdl2-mixer",
      "SPDXID": "SPDXRef-port",
      "versionInfo": "2.8.1#2",
      "downloadLocation": "git+https://github.com/Microsoft/vcpkg@ee2053a681764a5fda41536fee42df58397d0c37",
      "homepage": "https://github.com/libsdl-org/SDL_mixer",
      "licenseConcluded": "Zlib",
      "licenseDeclared": "NOASSERTION",
      "copyrightText": "NOASSERTION",
      "description": "Multi-channel audio mixer library for SDL.",
      "comment": "This is the port (recipe) consumed by vcpkg."
    },
    {
      "name": "sdl2-mixer:x64-mingw-dynamic",
      "SPDXID": "SPDXRef-binary",
      "versionInfo": "507207a94fadc9c7fb3f777cd75f945edfaac8c800325bfd997c82d47a9aa092",
      "downloadLocation": "NONE",
      "licenseConcluded": "Zlib",
      "licenseDeclared": "NOASSERTION",
      "copyrightText": "NOASSERTION",
      "comment": "This is a binary package built by vcpkg."
    },
    {
      "SPDXID": "SPDXRef-resource-0",
      "name": "libsdl-org/SDL_mixer",
      "downloadLocation": "git+https://github.com/libsdl-org/SDL_mixer@release-2.8.1",
      "licenseConcluded": "NOASSERTION",
      "licenseDeclared": "NOASSERTION",
      "copyrightText": "NOASSERTION",
      "checksums": [
        {
          "algorithm": "SHA512",
          "checksumValue": "653ec1f0af0b749b9ed0acd3bfcaa40e1e1ecf34af3127eb74019502ef42a551de226daef4cc89e6a51715f013e0ba0b1e48ae17d6aeee931271f2d10e82058a"
        }
      ]
    }
  ],
  "files": [
    {
      "fileName": "./fix-pkg-prefix.patch",
      "SPDXID": "SPDXRef-port-file-0",
      "checksums": [
        {
          "algorithm": "SHA256",
          "checksumValue": "14b1c2db9449402b392168410bb6012a4b0206d848a1d18801c7b4cfb19a717e"
        }
      ],
      "licenseConcluded": "NOASSERTION",
      "copyrightText": "NOASSERTION"
    },
    {
      "fileName": "./portfile.cmake",
      "SPDXID": "SPDXRef-port-file-1",
      "checksums": [
        {
          "algorithm": "SHA256",
          "checksumValue": "38483d54c796adfb555bbe310f49a3bf495e1d049fcfdac0f1ad26ca7b68e683"
        }
      ],
      "licenseConcluded": "NOASSERTION",
      "copyrightText": "NOASSERTION"
    },
    {
      "fileName": "./usage",
      "SPDXID": "SPDXRef-port-file-2",
      "checksums": [
        {
          "algorithm": "SHA256",
          "checksumValue": "03cd8f41347811ffd68422887573aaac82c130d058db4c2f494e5e0c46af5c7b"
        }
      ],
      "licenseConcluded": "NOASSERTION",
      "copyrightText": "NOASSERTION"
    },
    {
      "fileName": "./vcpkg.json",
      "SPDXID": "SPDXRef-port-file-3",
      "checksums": [
        {
          "algorithm": "SHA256",
          "checksumValue": "881dc728ed899f67e731c319a1ab16d5b5833181c945079ce855384e9c900313"
        }
      ],
      "licenseConcluded": "NOASSERTION",
      "copyrightText": "NOASSERTION"
    },
    {
      "fileName": "./bin/SDL2_mixer.dll",
      "SPDXID": "SPDXRef-binary-file-0",
      "checksums": [
        {
          "algorithm": "SHA256",
          "checksumValue": "57dc26693ab41355d687c06bb32a032b3bae44a3d1ba5ae935ef939222e449bc"
        }
      ],
      "licenseConcluded": "NOASSERTION",
      "copyrightText": "NOASSERTION"
    },
    {
      "fileName": "./BUILD_INFO",
      "SPDXID": "SPDXRef-binary-file-1",
      "checksums": [
        {
          "algorithm": "SHA256",
          "checksumValue": "6ab53fb9a3c8a8fd7267dfe9da42066bcaebbb691a450ba4a83145564fe9c597"
        }
      ],
      "licenseConcluded": "NOASSERTION",
      "copyrightText": "NOASSERTION"
    },
    {
      "fileName": "./debug/bin/SDL2_mixerd.dll",
      "SPDXID": "SPDXRef-binary-file-2",
      "checksums": [
        {
          "algorithm": "SHA256",
          "checksumValue": "e3aa730157f4d251cad611e23c6ba5b58f1156de60fe9fbc05277635fd1b5d1f"
        }
      ],
      "licenseConcluded": "NOASSERTION",
      "copyrightText": "NOASSERTION"
    },
    {
      "fileName": "./debug/lib/libSDL2_mixerd.dll.a",
      "SPDXID": "SPDXRef-binary-file-3",
      "checksums": [
        {
          "algorithm": "SHA256",
          "checksumValue": "fa6f03713a0d9ce33ca7664947ad5c9c817d5f1afa6edaa31476abe252d263a6"
        }
      ],
      "licenseConcluded": "NOASSERTION",
      "copyrightText": "NOASSERTION"
    },
    {
      "fileName": "./debug/lib/pkgconfig/SDL2_mixer.pc",
      "SPDXID": "SPDXRef-binary-file-4",
      "checksums": [
        {
          "algorithm": "SHA256",
          "checksumValue": "ac69122b89d5432f6ac3342b4248c35fba6823e544f358dcdfdf22146dc0e8f7"
        }
      ],
      "licenseConcluded": "NOASSERTION",
      "copyrightText": "NOASSERTION"
    },
    {
      "fileName": "./include/SDL2/SDL_mixer.h",
      "SPDXID": "SPDXRef-binary-file-5",
      "checksums": [
        {
          "algorithm": "SHA256",
          "checksumValue": "eefab9cf63472f03b93095bfa6bbd55bd203571155510a09d88e58410bc6436f"
        }
      ],
      "licenseConcluded": "NOASSERTION",
      "copyrightText": "NOASSERTION"
    },
    {
      "fileName": "./lib/libSDL2_mixer.dll.a",
      "SPDXID": "SPDXRef-binary-file-6",
      "checksums": [
        {
          "algorithm": "SHA256",
          "checksumValue": "a4dc10f2bbe38966f785dc69db714c802d28fa068b239f190e28efcb7841fd8b"
        }
      ],
      "licenseConcluded": "NOASSERTION",
      "copyrightText": "NOASSERTION"
    },
    {
      "fileName": "./lib/pkgconfig/SDL2_mixer.pc",
      "SPDXID": "SPDXRef-binary-file-7",
      "checksums": [
        {
          "algorithm": "SHA256",
          "checksumValue": "504eff68186c63dc45f55a96e71df98bc59db4907b77caed1ddc89f2d80a9c4c"
        }
      ],
      "licenseConcluded": "NOASSERTION",
      "copyrightText": "NOASSERTION"
    },
    {
      "fileName": "./share/licenses/SDL2_mixer/LICENSE.txt",
      "SPDXID": "SPDXRef-binary-file-8",
      "checksums": [
        {
          "algorithm": "SHA256",
          "checksumValue": "7826eca0a0f7e591f38dd844e207a200aac81a59b20d8a30c3af8c6282af13e6"
        }
      ],
      "licenseConcluded": "NOASSERTION",
      "copyrightText": "NOASSERTION"
    },
    {
      "fileName": "./share/sdl2-mixer/copyright",
      "SPDXID": "SPDXRef-binary-file-9",
      "checksums": [
        {
          "algorithm": "SHA256",
          "checksumValue": "7826eca0a0f7e591f38dd844e207a200aac81a59b20d8a30c3af8c6282af13e6"
        }
      ],
      "licenseConcluded": "NOASSERTION",
      "copyrightText": "NOASSERTION"
    },
    {
      "fileName": "./share/sdl2-mixer/usage",
      "SPDXID": "SPDXRef-binary-file-10",
      "checksums": [
        {
          "algorithm": "SHA256",
          "checksumValue": "03cd8f41347811ffd68422887573aaac82c130d058db4c2f494e5e0c46af5c7b"
        }
      ],
      "licenseConcluded": "NOASSERTION",
      "copyrightText": "NOASSERTION"
    },
    {
      "fileName": "./share/SDL2_mixer/SDL2_mixer-shared-targets-debug.cmake",
      "SPDXID": "SPDXRef-binary-file-11",
      "checksums": [
        {
          "algorithm": "SHA256",
          "checksumValue": "c1feb37a4202bc9842901d6aee8ca47f59a7f398a14b43a3fe0d35620185e487"
        }
      ],
      "licenseConcluded": "NOASSERTION",
      "copyrightText": "NOASSERTION"
    },
    {
      "fileName": "./share/SDL2_mixer/SDL2_mixer-shared-targets-release.cmake",
      "SPDXID": "SPDXRef-binary-file-12",
      "checksums": [
        {
          "algorithm": "SHA256",
          "checksumValue": "af64c94c7abd234a2fd8f154d981329c7811eff1ab53d4c2e5ed2de2e8df2791"
        }
      ],
      "licenseConcluded": "NOASSERTION",
      "copyrightText": "NOASSERTION"
    },
    {
      "fileName": "./share/SDL2_mixer/SDL2_mixer-shared-targets.cmake",
      "SPDXID": "SPDXRef-binary-file-13",
      "checksums": [
        {
          "algorithm": "SHA256",
          "checksumValue": "c93574dae982ae967b3ee7d53da40e2e8e27f9bf56a65dc994694988be6e579a"
        }
      ],
      "licenseConcluded": "NOASSERTION",
      "copyrightText": "NOASSERTION"
    },
    {
      "fileName": "./share/SDL2_mixer/SDL2_mixerConfig.cmake",
      "SPDXID": "SPDXRef-binary-file-14",
      "checksums": [
        {
          "algorithm": "SHA256",
          "checksumValue": "229ca83ed7a508f9f7fc6ae00c9a8d106fab080b34371803bc338c67aec71858"
        }
      ],
      "licenseConcluded": "NOASSERTION",
      "copyrightText": "NOASSERTION"
    },
    {
      "fileName": "./share/SDL2_mixer/SDL2_mixerConfigVersion.cmake",
      "SPDXID": "SPDXRef-binary-file-15",
      "checksums": [
        {
          "algorithm": "SHA256",
          "checksumValue": "635823d8e5e9df241b3c5c6ef41e9e7d2aa5d25fc5a02b4319eabdc2f27a45fc"
        }
      ],
      "licenseConcluded": "NOASSERTION",
      "copyrightText": "NOASSERTION"
    }
  ]
}
